README.rst
setup.cfg
setup.py
peek_mobile/__init__.py
peek_mobile/tslint.json
peek_mobile.egg-info/PKG-INFO
peek_mobile.egg-info/SOURCES.txt
peek_mobile.egg-info/dependency_links.txt
peek_mobile.egg-info/not-zip-safe
peek_mobile.egg-info/top_level.txt
peek_mobile/build-ns/_package_deleted_device_update_dependencies.json
peek_mobile/build-ns/package-lock.json
peek_mobile/build-ns/package.json
peek_mobile/build-ns/references.d.ts
peek_mobile/build-ns/tsconfig.aot.json
peek_mobile/build-ns/tsconfig.esm.json
peek_mobile/build-ns/tsconfig.json
peek_mobile/build-ns/webpack.config.js
peek_mobile/build-ns/app/_app-common.scss
peek_mobile/build-ns/app/app.android.scss
peek_mobile/build-ns/app/app.ios.scss
peek_mobile/build-ns/app/app.module.ts
peek_mobile/build-ns/app/main.aot.ts
peek_mobile/build-ns/app/main.ts
peek_mobile/build-ns/app/module-loader.ns.factory.ts
peek_mobile/build-ns/app/package.json
peek_mobile/build-ns/app/vendor-platform.android.ts
peek_mobile/build-ns/app/vendor-platform.ios.ts
peek_mobile/build-ns/app/vendor.ts
peek_mobile/build-ns/app/App_Resources/Android/AndroidManifest.xml
peek_mobile/build-ns/app/App_Resources/Android/app.gradle
peek_mobile/build-ns/app/App_Resources/Android/settings.gradle
peek_mobile/build-ns/app/App_Resources/Android/settings.json
peek_mobile/build-ns/app/App_Resources/Android/drawable-hdpi/background.png
peek_mobile/build-ns/app/App_Resources/Android/drawable-hdpi/icon.png
peek_mobile/build-ns/app/App_Resources/Android/drawable-hdpi/logo.png
peek_mobile/build-ns/app/App_Resources/Android/drawable-ldpi/background.png
peek_mobile/build-ns/app/App_Resources/Android/drawable-ldpi/icon.png
peek_mobile/build-ns/app/App_Resources/Android/drawable-ldpi/logo.png
peek_mobile/build-ns/app/App_Resources/Android/drawable-mdpi/background.png
peek_mobile/build-ns/app/App_Resources/Android/drawable-mdpi/icon.png
peek_mobile/build-ns/app/App_Resources/Android/drawable-mdpi/logo.png
peek_mobile/build-ns/app/App_Resources/Android/drawable-nodpi/splash_screen.xml
peek_mobile/build-ns/app/App_Resources/Android/drawable-xhdpi/background.png
peek_mobile/build-ns/app/App_Resources/Android/drawable-xhdpi/icon.png
