Metadata-Version: 1.1
Name: peek-mobile
Version: 2.5.2
Summary: Peek Platform - Mobile Service (Frontend)
Home-page: https://github.com/Synerty/peek-mobile
Author: Synerty
Author-email: contact@synerty.com
License: UNKNOWN
Download-URL: https://github.com/Synerty/peek-mobile/tarball/2.5.2
Keywords: Peek,Python,Platform,synerty
Platform: UNKNOWN
Classifier: Programming Language :: Python :: 3.5
